acm_auto_validate/__init__.py
acm_auto_validate/py.typed
acm_auto_validate/_jsii/__init__.py
acm_auto_validate/_jsii/acm-auto-validate@0.0.5.jsii.tgz
acm_auto_validate-0.0.5.dist-info/LICENSE
acm_auto_validate-0.0.5.dist-info/METADATA
acm_auto_validate-0.0.5.dist-info/WHEEL
acm_auto_validate-0.0.5.dist-info/top_level.txt
acm_auto_validate-0.0.5.dist-info/RECORD
